notify_me_tool/__init__.py
notify_me_tool/hookspecs.py
notify_me_tool/host.py
notify_me_tool/lib.py
notify_me_tool-0.1.1.dist-info/entry_points.txt
notify_me_tool-0.1.1.dist-info/WHEEL
notify_me_tool-0.1.1.dist-info/METADATA
notify_me_tool-0.1.1.dist-info/RECORD
